<annotation>
	<folder></folder>
	<filename>10072_jpg.rf.bd744ac9d17c6c9d630e05e184b6440b.jpg</filename>
	<path>10072_jpg.rf.bd744ac9d17c6c9d630e05e184b6440b.jpg</path>
	<source>
		<database>roboflow.com</database>
	</source>
	<size>
		<width>225</width>
		<height>225</height>
		<depth>3</depth>
	</size>
	<segmented>0</segmented>
	<object>
		<name>Ear_protector</name>
		<pose>Unspecified</pose>
		<truncated>0</truncated>
		<difficult>0</difficult>
		<occluded>0</occluded>
		<bndbox>
			<xmin>24</xmin>
			<xmax>108</xmax>
			<ymin>125</ymin>
			<ymax>226</ymax>
		</bndbox>
	</object>
	<object>
		<name>Ear_protector</name>
		<pose>Unspecified</pose>
		<truncated>0</truncated>
		<difficult>0</difficult>
		<occluded>0</occluded>
		<bndbox>
			<xmin>116</xmin>
			<xmax>180</xmax>
			<ymin>130</ymin>
			<ymax>210</ymax>
		</bndbox>
	</object>
	<object>
		<name>Hard_hat</name>
		<pose>Unspecified</pose>
		<truncated>0</truncated>
		<difficult>0</difficult>
		<occluded>0</occluded>
		<bndbox>
			<xmin>1</xmin>
			<xmax>222</xmax>
			<ymin>1</ymin>
			<ymax>121</ymax>
		</bndbox>
	</object>
	<metadata>
	</metadata>
</annotation>
